abrax/__init__.py
abrax/compiler.py
abrax/parser.py
abrax/utils.py
tests/__init__.py
tests/braket.py
tests/cirq.py
tests/cudaq.py
tests/penny.py
tests/qiskit.py
tests/quil.py
tests/tket.py
tests/utils.py
abrax-1.2.1.dist-info/LICENSE
abrax-1.2.1.dist-info/METADATA
abrax-1.2.1.dist-info/WHEEL
abrax-1.2.1.dist-info/top_level.txt
abrax-1.2.1.dist-info/RECORD
