Metadata-Version: 2.1
Name: abrax
Version: 1.2.1
Summary: Cross platform circuit transpiler
Home-page: https://github.com/plutoniumm/abraxas
Author: plutoniumm
License: MIT
Requires-Python: >=3.9
License-File: LICENSE
Requires-Dist: numpy
Requires-Dist: qiskit
Provides-Extra: dev
Requires-Dist: pytest ; extra == 'dev'
Requires-Dist: twine ; extra == 'dev'
Requires-Dist: wheel ; extra == 'dev'
